sqlgym/__init__.py
sqlgym/sqlgym.py
sqlgym/datasets/__init__.py
sqlgym/datasets/bird.py
sqlgym/datasets/utils.py
sqlgym-0.1.2.dist-info/METADATA
sqlgym-0.1.2.dist-info/WHEEL
sqlgym-0.1.2.dist-info/top_level.txt
sqlgym-0.1.2.dist-info/RECORD
