Metadata-Version: 2.1
Name: sqlgym
Version: 0.1.2
Summary: SQLGym: A portable Gymnasium environment of SQLite database.
Author-email: KYLN24 <1296845690@qq.com>
Project-URL: Repository, https://github.com/KYLN24/sqlgym.git
Requires-Python: >=3.8
Requires-Dist: gymnasium
Requires-Dist: tqdm
Provides-Extra: react
Requires-Dist: openai ; extra == 'react'
Provides-Extra: sft
Requires-Dist: sqlgym[react] ; extra == 'sft'
Requires-Dist: torch ; extra == 'sft'
Requires-Dist: transformers ; extra == 'sft'
Requires-Dist: deepspeed ; extra == 'sft'
Requires-Dist: datasets ; extra == 'sft'
Requires-Dist: accelerate ; extra == 'sft'
